mindcv/__init__.py
mindcv/version.py
mindcv/data/__init__.py
mindcv/data/auto_augment.py
mindcv/data/constants.py
mindcv/data/dataset_download.py
mindcv/data/dataset_factory.py
mindcv/data/distributed_sampler.py
mindcv/data/loader.py
mindcv/data/mixup.py
mindcv/data/transforms_factory.py
mindcv/loss/__init__.py
mindcv/loss/asymmetric.py
mindcv/loss/binary_cross_entropy_smooth.py
mindcv/loss/cross_entropy_smooth.py
mindcv/loss/jsd.py
mindcv/loss/loss_factory.py
mindcv/models/__init__.py
mindcv/models/bit.py
mindcv/models/cait.py
mindcv/models/cmt.py
mindcv/models/coat.py
mindcv/models/convit.py
mindcv/models/convnext.py
mindcv/models/crossvit.py
mindcv/models/densenet.py
mindcv/models/dpn.py
mindcv/models/edgenext.py
mindcv/models/efficientnet.py
mindcv/models/features.py
mindcv/models/ghostnet.py
mindcv/models/googlenet.py
mindcv/models/halonet.py
mindcv/models/helpers.py
mindcv/models/hrnet.py
mindcv/models/inceptionv3.py
mindcv/models/inceptionv4.py
mindcv/models/mae.py
mindcv/models/mixnet.py
mindcv/models/mlpmixer.py
mindcv/models/mnasnet.py
mindcv/models/mobilenetv1.py
mindcv/models/mobilenetv2.py
mindcv/models/mobilenetv3.py
mindcv/models/mobilevit.py
mindcv/models/model_factory.py
mindcv/models/nasnet.py
mindcv/models/pit.py
mindcv/models/pnasnet.py
mindcv/models/poolformer.py
mindcv/models/pvt.py
mindcv/models/pvtv2.py
mindcv/models/registry.py
mindcv/models/regnet.py
mindcv/models/repmlp.py
mindcv/models/repvgg.py
mindcv/models/res2net.py
mindcv/models/resnest.py
mindcv/models/resnet.py
mindcv/models/resnetv2.py
mindcv/models/rexnet.py
mindcv/models/senet.py
mindcv/models/shufflenetv1.py
mindcv/models/shufflenetv2.py
mindcv/models/sknet.py
mindcv/models/squeezenet.py
mindcv/models/swintransformer.py
mindcv/models/swintransformerv2.py
mindcv/models/vgg.py
mindcv/models/visformer.py
mindcv/models/vit.py
mindcv/models/volo.py
mindcv/models/xception.py
mindcv/models/xcit.py
mindcv/models/layers/__init__.py
mindcv/models/layers/activation.py
mindcv-0.3.0.dist-info/LICENSE.md
mindcv-0.3.0.dist-info/METADATA
mindcv-0.3.0.dist-info/WHEEL
mindcv-0.3.0.dist-info/top_level.txt
mindcv-0.3.0.dist-info/RECORD
