Metadata-Version: 2.1
Name: mindcv
Version: 0.3.0
Summary: A toolbox of vision models and algorithms based on MindSpore.
Home-page: https://github.com/mindspore-lab/mindcv
Author: MindSpore Lab
Author-email: mindspore-lab@example.com
License: Apache Software License 2.0
Project-URL: Sources, https://github.com/mindspore-lab/mindcv
Project-URL: Issue Tracker, https://github.com/mindspore-lab/mindcv/issues
Classifier: Development Status :: 2 - Pre-Alpha
Classifier: Intended Audience :: Developers
Classifier: License :: OSI Approved :: Apache Software License
Classifier: Natural Language :: English
Classifier: Programming Language :: Python :: 3
Classifier: Programming Language :: Python :: 3.7
Classifier: Programming Language :: Python :: 3.8
Classifier: Programming Language :: Python :: 3.9
Requires-Python: >=3.7
License-File: LICENSE.md
Requires-Dist: numpy >=1.17.0
Requires-Dist: PyYAML >=5.3
Requires-Dist: tqdm
